{
    "1010": "Banks",
    "1020": "Banks",
    "1030": "Banks",
    "1040": "Tadawul All Share Index (TASI)",
    "1050": "Banks",
    "1060": "Banks",
    "1080": "Banks",
    "1090": "Banks",
    "1111": "Financial Services",
    "1120": "Banks",
    "1140": "Banks",
    "1150": "Banks",
    "1180": "Banks",
    "1182": "Financial Services",
    "1183": "Financial Services",
    "1201": "Materials",
    "1202": "Materials",
    "1210": "Materials",
    "1211": "Materials",
    "1212": "Capital Goods",
    "1213": "Consumer Durables & Apparel",
    "1214": "Capital Goods",
    "1301": "Materials",
    "1302": "Capital Goods",
    "1303": "Capital Goods",
    "1304": "Materials",
    "1310": "Capital Goods",
    "1320": "Materials",
    "1321": "Materials",
    "1322": "Materials",
    "1323": "Materials",
    "1330": "Capital Goods",
    "1810": "Consumer Services",
    "1820": "Consumer Services",
    "1830": "Consumer Services",
    "1831": "Commercial & Professional Svc",
    "1832": "Commercial & Professional Svc",
    "1833": "Commercial & Professional Svc",
    "1834": "Commercial & Professional Svc",
    "1835": "Commercial & Professional Svc",
    "2001": "Materials",
    "2002": "Materials",
    "2010": "Materials",
    "2020": "Materials",
    "2030": "Energy",
    "2040": "Capital Goods",
    "2050": "Food & Beverages",
    "2060": "Materials",
    "2070": "Pharma &  Biotech & Life Science",
    "2080": "Utilities",
    "2081": "Utilities",
    "2082": "Utilities",
    "2083": "Utilities",
    "2084": "Utilities",
    "2090": "Materials",
    "2100": "Food & Beverages",
    "2110": "Capital Goods",
    "2120": "Financial Services",
    "2130": "Consumer Durables & Apparel",
    "2140": "Health Care Equipment & Svc",
    "2150": "Materials",
    "2160": "Capital Goods",
    "2170": "Materials",
    "2180": "Materials",
    "2190": "Transportation",
    "2200": "Materials",
    "2210": "Materials",
    "2220": "Materials",
    "2222": "Energy",
    "2223": "Materials",
    "2230": "Health Care Equipment & Svc",
    "2240": "Materials",
    "2250": "Materials",
    "2260": "Materials",
    "2270": "Food & Beverages",
    "2280": "Food & Beverages",
    "2281": "Food & Beverages",
    "2282": "Food & Beverages",
    "2283": "Food & Beverages",
    "2284": "Food & Beverages",
    "2285": "Food & Beverages",
    "2286": "Food & Beverages",
    "2287": "Food & Beverages",
    "2290": "Materials",
    "2300": "Materials",
    "2310": "Materials",
    "2320": "Capital Goods",
    "2330": "Materials",
    "2340": "Consumer Durables & Apparel",
    "2350": "Materials",
    "2360": "Materials",
    "2370": "Capital Goods",
    "2380": "Energy",
    "2381": "Energy",
    "2382": "Energy",
    "3001": "Materials",
    "3002": "Materials",
    "3003": "Materials",
    "3004": "Materials",
    "3005": "Materials",
    "3007": "Materials",
    "3008": "Materials",
    "3010": "Materials",
    "3020": "Materials",
    "3030": "Materials",
    "3040": "Materials",
    "3050": "Materials",
    "3060": "Materials",
    "3080": "Materials",
    "3090": "Materials",
    "3091": "Materials",
    "3092": "Materials",
    "4001": "Consumer Staples Distribution & Retail",
    "4002": "Health Care Equipment & Svc",
    "4003": "Consumer Discretionary Distribution & Retail",
    "4004": "Health Care Equipment & Svc",
    "4005": "Health Care Equipment & Svc",
    "4006": "Consumer Staples Distribution & Retail",
    "4007": "Health Care Equipment & Svc",
    "4008": "Consumer Discretionary Distribution & Retail",
    "4009": "Health Care Equipment & Svc",
    "4010": "Consumer Services",
    "4011": "Consumer Durables & Apparel",
    "4012": "Consumer Durables & Apparel",
    "4013": "Health Care Equipment & Svc",
    "4014": "Health Care Equipment & Svc",
    "4015": "Pharma &  Biotech & Life Science",
    "4016": "Pharma &  Biotech & Life Science",
    "4017": "Health Care Equipment & Svc",
    "4018": "Health Care Equipment & Svc",
    "4019": "Health Care Equipment & Svc",
    "4020": "Real Estate Mgmt & Dev't",
    "4021": "Health Care Equipment & Svc",
    "4030": "Energy",
    "4031": "Transportation",
    "4040": "Transportation",
    "4050": "Consumer Discretionary Distribution & Retail",
    "4051": "Consumer Discretionary Distribution & Retail",
    "4061": "Consumer Staples Distribution & Retail",
    "4070": "Media and Entertainment",
    "4071": "Media and Entertainment",
    "4072": "Media and Entertainment",
    "4080": "Food & Beverages",
    "4081": "Financial Services",
    "4082": "Financial Services",
    "4083": "Financial Services",
    "4084": "Financial Services",
    "4090": "Real Estate Mgmt & Dev't",
    "4100": "Real Estate Mgmt & Dev't",
    "4110": "Capital Goods",
    "4130": "Financial Services",
    "4140": "Capital Goods",
    "4141": "Capital Goods",
    "4142": "Capital Goods",
    "4143": "Materials",
    "4144": "Capital Goods",
    "4145": "Capital Goods",
    "4146": "Capital Goods",
    "4147": "Capital Goods",
    "4150": "Real Estate Mgmt & Dev't",
    "4160": "Consumer Staples Distribution & Retail",
    "4161": "Consumer Staples Distribution & Retail",
    "4162": "Consumer Staples Distribution & Retail",
    "4163": "Consumer Staples Distribution & Retail",
    "4164": "Consumer Staples Distribution & Retail",
    "4165": "Household & Personal Products",
    "4170": "Consumer Services",
    "4180": "Consumer Durables & Apparel",
    "4190": "Consumer Discretionary Distribution & Retail",
    "4191": "Consumer Discretionary Distribution & Retail",
    "4192": "Consumer Discretionary Distribution & Retail",
    "4193": "Consumer Discretionary Distribution & Retail",
    "4194": "Consumer Discretionary Distribution & Retail",
    "4200": "Consumer Discretionary Distribution & Retail",
    "4210": "Media and Entertainment",
    "4220": "Real Estate Mgmt & Dev't",
    "4230": "Real Estate Mgmt & Dev't",
    "4240": "Consumer Discretionary Distribution & Retail",
    "4250": "Real Estate Mgmt & Dev't",
    "4260": "Transportation",
    "4261": "Transportation",
    "4262": "Transportation",
    "4263": "Transportation",
    "4264": "Transportation",
    "4265": "Transportation",
    "4270": "Commercial & Professional Svc",
    "4280": "Financial Services",
    "4290": "Consumer Services",
    "4291": "Consumer Services",
    "4292": "Consumer Services",
    "4300": "Real Estate Mgmt & Dev't",
    "4310": "Real Estate Mgmt & Dev't",
    "4320": "Real Estate Mgmt & Dev't",
    "4321": "Real Estate Mgmt & Dev't",
    "4322": "Real Estate Mgmt & Dev't",
    "4323": "Real Estate Mgmt & Dev't",
    "4324": "Real Estate Mgmt & Dev't",
    "4325": "Real Estate Mgmt & Dev't",
    "4326": "Real Estate Mgmt & Dev't",
    "4327": "Real Estate Mgmt & Dev't",
    "4330": "REITs",
    "4331": "REITs",
    "4332": "REITs",
    "4333": "REITs",
    "4334": "REITs",
    "4335": "REITs",
    "4336": "REITs",
    "4337": "REITs",
    "4338": "REITs",
    "4339": "REITs",
    "4340": "REITs",
    "4342": "REITs",
    "4344": "REITs",
    "4345": "REITs",
    "4346": "REITs",
    "4347": "REITs",
    "4348": "REITs",
    "4349": "REITs",
    "4350": "REITs",
    "5110": "Utilities",
    "6001": "Food & Beverages",
    "6002": "Consumer Services",
    "6004": "Commercial & Professional Svc",
    "6010": "Food & Beverages",
    "6012": "Consumer Services",
    "6013": "Consumer Services",
    "6014": "Consumer Services",
    "6015": "Consumer Services",
    "6016": "Consumer Services",
    "6017": "Consumer Services",
    "6018": "Consumer Services",
    "6019": "Consumer Services",
    "6020": "Food & Beverages",
    "6030": "Food & Beverages",
    "6040": "Food & Beverages",
    "6050": "Food & Beverages",
    "6060": "Food & Beverages",
    "6070": "Food & Beverages",
    "6080": "Materials",
    "6090": "Food & Beverages",
    "7010": "Telecommunication Services",
    "7020": "Telecommunication Services",
    "7030": "Telecommunication Services",
    "7040": "Telecommunication Services",
    "7050": "Telecommunication Services",
    "7200": "Software & Services",
    "7201": "Software & Services",
    "7202": "Software & Services",
    "7203": "Software & Services",
    "7204": "Software & Services",
    "7211": "Software & Services",
    "8010": "Insurance",
    "8011": "Insurance",
    "8012": "Insurance",
    "8020": "Insurance",
    "8030": "Insurance",
    "8040": "Insurance",
    "8050": "Insurance",
    "8060": "Insurance",
    "8070": "Insurance",
    "8080": "Insurance",
    "8090": "Insurance",
    "8100": "Insurance",
    "8110": "Insurance",
    "8120": "Insurance",
    "8130": "Insurance",
    "8140": "Insurance",
    "8150": "Insurance",
    "8160": "Insurance",
    "8170": "Insurance",
    "8180": "Insurance",
    "8190": "Insurance",
    "8200": "Insurance",
    "8210": "Insurance",
    "8220": "Insurance",
    "8230": "Insurance",
    "8240": "Insurance",
    "8250": "Insurance",
    "8260": "Insurance",
    "8270": "Insurance",
    "8280": "Insurance",
    "8290": "Insurance",
    "8300": "Insurance",
    "8310": "Insurance",
    "8311": "Insurance",
    "8312": "Insurance",
    "8313": "Insurance"
}